[[{"__type__":"cc.Prefab","_name":"PayTable","data":{"__id__":1}},{"__type__":"cc.Node","_name":"PayTable","_children":[{"__id__":2},{"__id__":3}],"_components":[{"__type__":"cc.Widget","node":{"__id__":1},"_alignFlags":45},{"__type__":"4427fAPsaFA97eEIcUIGNWa","node":{"__id__":1}}],"_prefab":{"__type__":"cc.PrefabInfo","root":{"__id__":1},"asset":{"__uuid__":"80pW/UGwFCHKVQXS6f6Eik"},"fileId":"27+3oUNg5HPKzH1givxwCs"},"_contentSize":{"__type__":"cc.Size","width":750,"height":1334},"_trs":{"__type__":"TypedArray","ctor":"Float64Array","array":[375,667,0,0,0,0,1,1,1,1]}},{"__type__":"cc.Node","_name":"block","_parent":{"__id__":1},"_components":[{"__type__":"cc.Sprite","node":{"__id__":2},"_materials":[{"__uuid__":"ecpdLyjvZBwrvm+cedCcQy"}],"_spriteFrame":{"__uuid__":"a2MjXRFdtLlYQ5ouAFv/+R"},"_sizeMode":0},{"__type__":"cc.Widget","node":{"__id__":2},"_alignFlags":45,"_originalWidth":2,"_originalHeight":2},{"__type__":"cc.BlockInputEvents","node":{"__id__":2}}],"_prefab":{"__type__":"cc.PrefabInfo","root":{"__id__":1},"asset":{"__uuid__":"80pW/UGwFCHKVQXS6f6Eik"},"fileId":"3dqEGjujhB8oxawYJ1MNPx"},"_opacity":50,"_color":{"__type__":"cc.Color"},"_contentSize":{"__type__":"cc.Size","width":750,"height":1334},"_trs":{"__type__":"TypedArray","ctor":"Float64Array","array":[0,0,0,0,0,0,1,1,1,1]}},{"__type__":"cc.Node","_name":"bg","_parent":{"__id__":1},"_children":[{"__id__":4},{"__id__":5},{"__id__":6},{"__id__":7}],"_components":[{"__type__":"cc.Sprite","node":{"__id__":3},"_materials":[{"__uuid__":"ecpdLyjvZBwrvm+cedCcQy"}],"_spriteFrame":{"__uuid__":"c9DaWGBX1PF6ebtk0o8OTc"},"_sizeMode":0}],"_prefab":{"__type__":"cc.PrefabInfo","root":{"__id__":1},"asset":{"__uuid__":"80pW/UGwFCHKVQXS6f6Eik"},"fileId":"ecMOJZlbVLoomr+ZjvkdFH"},"_contentSize":{"__type__":"cc.Size","width":696,"height":901},"_trs":{"__type__":"TypedArray","ctor":"Float64Array","array":[0,0,0,0,0,0,1,1,1,1]}},{"__type__":"cc.Node","_name":"title","_parent":{"__id__":3},"_components":[{"__type__":"cc.Label","node":{"__id__":4},"_materials":[{"__uuid__":"ecpdLyjvZBwrvm+cedCcQy"}],"_string":"PAY TABLE","_N$string":"PAY TABLE","_fontSize":80,"_lineHeight":80,"_N$file":{"__uuid__":"f7zhWX2Z9O6bfUKktwYKzV"},"_isSystemFontUsed":false,"_N$horizontalAlign":1,"_N$verticalAlign":1}],"_prefab":{"__type__":"cc.PrefabInfo","root":{"__id__":1},"asset":{"__uuid__":"80pW/UGwFCHKVQXS6f6Eik"},"fileId":"fbMgzWtPZFWbJk2QebRhCy"},"_contentSize":{"__type__":"cc.Size","width":227,"height":80},"_trs":{"__type__":"TypedArray","ctor":"Float64Array","array":[0,300,0,0,0,0,1,1,1,1]}},{"__type__":"cc.Node","_name":"blackjack","_parent":{"__id__":3},"_components":[{"__type__":"cc.Label","node":{"__id__":5},"_materials":[{"__uuid__":"ecpdLyjvZBwrvm+cedCcQy"}],"_string":"Blackjacks pay 3 to 2","_N$string":"Blackjacks pay 3 to 2","_fontSize":80,"_lineHeight":80,"_N$file":{"__uuid__":"f7zhWX2Z9O6bfUKktwYKzV"},"_isSystemFontUsed":false,"_N$horizontalAlign":1,"_N$verticalAlign":1}],"_prefab":{"__type__":"cc.PrefabInfo","root":{"__id__":1},"asset":{"__uuid__":"80pW/UGwFCHKVQXS6f6Eik"},"fileId":"2et5mmhrBBg6nqiEzooLFZ"},"_contentSize":{"__type__":"cc.Size","width":454,"height":80},"_trs":{"__type__":"TypedArray","ctor":"Float64Array","array":[0,150,0,0,0,0,1,1,1,1]}},{"__type__":"cc.Node","_name":"push","_parent":{"__id__":3},"_components":[{"__type__":"cc.Label","node":{"__id__":6},"_materials":[{"__uuid__":"ecpdLyjvZBwrvm+cedCcQy"}],"_string":"Dealer pushes on 22","_N$string":"Dealer pushes on 22","_fontSize":80,"_lineHeight":80,"_N$file":{"__uuid__":"f7zhWX2Z9O6bfUKktwYKzV"},"_isSystemFontUsed":false,"_N$horizontalAlign":1,"_N$verticalAlign":1}],"_prefab":{"__type__":"cc.PrefabInfo","root":{"__id__":1},"asset":{"__uuid__":"80pW/UGwFCHKVQXS6f6Eik"},"fileId":"6dZbAXnNRKgbr5cuZbV9s1"},"_contentSize":{"__type__":"cc.Size","width":431,"height":80},"_trs":{"__type__":"TypedArray","ctor":"Float64Array","array":[0,0,0,0,0,0,1,1,1,1]}},{"__type__":"cc.Node","_name":"ok","_parent":{"__id__":3},"_children":[{"__id__":8}],"_components":[{"__type__":"cc.Button","node":{"__id__":7},"clickEvents":[{"__type__":"cc.ClickEvent","target":{"__id__":1},"_componentId":"4427fAPsaFA97eEIcUIGNWa","handler":"onOkClick"}],"_N$target":{"__id__":7}}],"_prefab":{"__type__":"cc.PrefabInfo","root":{"__id__":1},"asset":{"__uuid__":"80pW/UGwFCHKVQXS6f6Eik"},"fileId":"7eTNOIlvdB0penUEo6t5I1"},"_contentSize":{"__type__":"cc.Size","width":640,"height":100},"_trs":{"__type__":"TypedArray","ctor":"Float64Array","array":[0,-375,0,0,0,0,1,1,1,1]}},{"__type__":"cc.Node","_name":"label","_parent":{"__id__":7},"_components":[{"__type__":"cc.Label","node":{"__id__":8},"_materials":[{"__uuid__":"ecpdLyjvZBwrvm+cedCcQy"}],"_string":"OK","_N$string":"OK","_fontSize":50,"_lineHeight":50,"_N$file":{"__uuid__":"e6O6HhvtJJkZaSmzjEhFg/"},"_isSystemFontUsed":false,"_N$horizontalAlign":1,"_N$verticalAlign":1}],"_prefab":{"__type__":"cc.PrefabInfo","root":{"__id__":1},"asset":{"__uuid__":"80pW/UGwFCHKVQXS6f6Eik"},"fileId":"44ZgqCVZNEYoMQzYYII2rq"},"_color":{"__type__":"cc.Color","r":107,"g":255,"b":255},"_contentSize":{"__type__":"cc.Size","width":75.63,"height":50},"_trs":{"__type__":"TypedArray","ctor":"Float64Array","array":[0,0,0,0,0,0,1,1,1,1]}}],{"__type__":"cc.SpriteFrame","content":{"name":"paytable","texture":"d67ts6BNxCYYaIvSKo0bNO","rect":[0,0,1392,1802],"offset":[0,0],"originalSize":[1392,1802],"capInsets":[0,0,0,0]}}]